{
  "intensity": 0.372,
  "awakenedEngine": {
    "enabled": true,
    "progression": "base",
    "awakenedThreshold": 0.457,
    "ascendedThreshold": 0.776,
    "distortionMultiplier": 0.998,
    "particleMultiplier": 1.121,
    "colorIntensity": 1.06,
    "glitchFrequency": 0.045,
    "energyRings": false
  },
  "date": "2026-04-22",
  "timestamp": 1776876016274,
  "updatedAt": "Wed Apr 22 16:40:16 UTC 2026",
  "source": "farcaster-awakened",
  "metrics": {
    "casts": 10,
    "likes": 0,
    "recasts": 0
  }
}
